tag_aaron_alphabet/__init__.py
tag_leverage_aaron_alphabet-0.0.1.dist-info/METADATA
tag_leverage_aaron_alphabet-0.0.1.dist-info/WHEEL
tag_leverage_aaron_alphabet-0.0.1.dist-info/top_level.txt
tag_leverage_aaron_alphabet-0.0.1.dist-info/RECORD
