Metadata-Version: 2.1
Name: tag-leverage-aaron-alphabet
Version: 0.0.1
Summary: tagging files
Author-email: Aaron Alphabet <aaron.alphabet@posteo.org>
Classifier: License :: OSI Approved :: MIT License
Classifier: Programming Language :: Python :: 3
Requires-Python: >=3.11
Requires-Dist: tomli-w (>=1.0.0)
